pypiuploader/__init__.py
pypiuploader/commands.py
pypiuploader/download.py
pypiuploader/exceptions.py
pypiuploader/pypirc.py
pypiuploader/upload.py
pypi_uploader2-1.1.1.dist-info/LICENSE
pypi_uploader2-1.1.1.dist-info/METADATA
pypi_uploader2-1.1.1.dist-info/WHEEL
pypi_uploader2-1.1.1.dist-info/entry_points.txt
pypi_uploader2-1.1.1.dist-info/top_level.txt
pypi_uploader2-1.1.1.dist-info/RECORD
