Metadata-Version: 2.1
Name: pypi-uploader2
Version: 1.1.1
Summary: Upload source distributions to your PyPI server.
Home-page: https://github.com/victorwang0526/pypi_uploader
Author: Victor Wang
Author-email: fengxuanwang0526@gmail.com
License: Copyright (c) 2019 Victor Wang
Requires-Dist: requests
Requires-Dist: pip (>=8)
